MANIFEST.in
README.rst
setup.py
django_numerics.egg-info/PKG-INFO
django_numerics.egg-info/SOURCES.txt
django_numerics.egg-info/dependency_links.txt
django_numerics.egg-info/not-zip-safe
django_numerics.egg-info/top_level.txt
djangonumerics/__init__.py
djangonumerics/admin.py
djangonumerics/api.py
djangonumerics/exceptions.py
djangonumerics/forms.py
djangonumerics/models.py
djangonumerics/responses.py
djangonumerics/serializers.py
djangonumerics/urls.py
djangonumerics/utils.py
djangonumerics/views.py
djangonumerics/migrations/__init__.py
djangonumerics/static/.DS_Store
djangonumerics/static/djangonumerics/.DS_Store
djangonumerics/static/djangonumerics/images/.DS_Store
djangonumerics/static/djangonumerics/images/basic_label.jpg
djangonumerics/static/djangonumerics/images/basic_number.jpg
djangonumerics/static/djangonumerics/images/choose_service.jpg
djangonumerics/static/djangonumerics/images/json_view.jpg
djangonumerics/static/djangonumerics/styles/help.css
djangonumerics/static/djangonumerics/styles/help.css~
djangonumerics/static/djangonumerics/styles/main.css
djangonumerics/static/djangonumerics/styles/main.css~
djangonumerics/templates/djangonumerics/base.html
djangonumerics/templates/djangonumerics/base.html~
djangonumerics/templates/djangonumerics/help.html
djangonumerics/templates/djangonumerics/help.html~
djangonumerics/templates/djangonumerics/index.html
djangonumerics/templates/djangonumerics/index.html~
tests/__init__.py
tests/base.py
tests/test_api.py
tests/test_responses.py
tests/test_serializers.py
tests/test_views.py