Metadata-Version: 1.0
Name: django-numerics
Version: 0.2.0
Summary: numerics dashboard endpoint provider for django.
Home-page: https://github.com/huseyinyilmaz/django-numerics
Author: Huseyin Yilmaz
Author-email: yilmazhuseyin@gmail.com
License: UNKNOWN
Platform: UNKNOWN
